MANIFEST.in
README.rst
bootstrap.py
buildout.cfg
setup.py
docs/HISTORY.txt
plone/__init__.py
plone.app.s5slideshow.egg-info/PKG-INFO
plone.app.s5slideshow.egg-info/SOURCES.txt
plone.app.s5slideshow.egg-info/dependency_links.txt
plone.app.s5slideshow.egg-info/entry_points.txt
plone.app.s5slideshow.egg-info/namespace_packages.txt
plone.app.s5slideshow.egg-info/not-zip-safe
plone.app.s5slideshow.egg-info/requires.txt
plone.app.s5slideshow.egg-info/top_level.txt
plone/app/__init__.py
plone/app/s5slideshow/__init__.py
plone/app/s5slideshow/configure.zcml
plone/app/s5slideshow/extender.py
plone/app/s5slideshow/interfaces.py
plone/app/s5slideshow/presentation.pt
plone/app/s5slideshow/presentation.py
plone/app/s5slideshow/profiles/default/browserlayer.xml
plone/app/s5slideshow/profiles/default/metadata.xml
plone/app/s5slideshow/resources/s5_core.css
plone/app/s5slideshow/resources/s5_framing.css
plone/app/s5slideshow/resources/s5_iepngfix.htc
plone/app/s5slideshow/resources/s5_opera.css
plone/app/s5slideshow/resources/s5_outline.css
plone/app/s5slideshow/resources/s5_pretty.css
plone/app/s5slideshow/resources/s5_print.css
plone/app/s5slideshow/resources/s5_slides.css
plone/app/s5slideshow/resources/s5_slides.js
plone/app/s5slideshow/tests/__init__.py
plone/app/s5slideshow/tests/test_presentation.py