Metadata-Version: 1.1
Name: plone.app.s5slideshow
Version: 1.0
Summary: S5 Slideshow plone integration
Home-page: http://svn.plone.org/svn/collective/
Author: UNKNOWN
Author-email: UNKNOWN
License: GPL
Platform: UNKNOWN
Classifier: Programming Language :: Python
